{
    "basic_info": {
      "name": "Thảo Nguyễn",
      "titles": [ "Full-stack Web Developer", "Mobile App Developer", "Android App Developer" ],
      "social": [
        {
          "name": "github",
          "url": "https://github.com/npthao1312",
          "class": "fab fa-github"
        },
        {
          "name": "facebook",
          "url": "https://www.facebook.com/thaonp.1312/",
          "class": "fab fa-facebook"
        },
        {
          "name": "linkedin",
          "url": "https://www.linkedin.com/in/thao-nguyen-009177125/",
          "class": "fab fa-linkedin"
        }
      ],
      "image": "profile_pic.png"
    },
    "skills": {
      "icons": [
        {
          "name": "HTML 5",
          "class": "devicon-html5-plain",
          "level": "95"
        },
        {
          "name": "CSS 3",
          "class": "devicon-css3-plain",
          "level": "95"
        },
        {
          "name": "ReactJS",
          "class": "devicon-react-plain",
          "level": "70"
        },
        {
          "name": "TypeScript",
          "class": "devicon-typescript-plain",
          "level": "90"
        },
        {
          "name": "JavaScript",
          "class": "devicon-javascript-plain",
          "level": "70"
        },
        {
          "name": "Python",
          "class": "devicon-python-plain",
          "level": "70"
        },
        {
          "name": "Java",
          "class": "devicon-java-plain",
          "level": "70"
        },
        {
          "name": "NodeJS",
          "class": "devicon-nodejs-plain",
          "level": "70"
        },
        {
          "name": "Sass",
          "class": "devicon-sass-original",
          "level": "75"
        },
        {
          "name": "Bootstrap",
          "class": "devicon-bootstrap-plain",
          "level": "85"
        },
        {
          "name": "C/C#",
          "class": "devicon-csharp-plain",
          "level": "65"
        },
        {
          "name": "MySql",
          "class": "devicon-mysql-plain",
          "level": "70"
        }
      ]
    }
  }
